onnxifier/__init__.py
onnxifier/__main__.py
onnxifier/checker.py
onnxifier/graph.py
onnxifier/logger.py
onnxifier/pass_manager.py
onnxifier/py.typed
onnxifier/traits.py
onnxifier/utils.py
onnxifier/algo/subgraph.py
onnxifier/domain/README.md
onnxifier/domain/__init__.py
onnxifier/domain/intel/__init__.py
onnxifier/domain/intel/openvino/__init__.py
onnxifier/domain/intel/openvino/utils.py
onnxifier/domain/intel/openvino/xml_frontend.py
onnxifier/domain/intel/openvino/ir/__init__.py
onnxifier/domain/intel/openvino/ir/ir11.py
onnxifier/domain/intel/openvino/ir/mapping.py
onnxifier/domain/intel/openvino/passes/__init__.py
onnxifier/domain/intel/openvino/passes/eliminate_useless_floor.py
onnxifier/domain/intel/openvino/passes/shapeof_to_constant.py
onnxifier/domain/intel/openvino/passes/op/__init__.py
onnxifier/domain/intel/openvino/passes/op/avgpool.py
onnxifier/domain/intel/openvino/passes/op/batch_norm_inference.py
onnxifier/domain/intel/openvino/passes/op/broadcast.py
onnxifier/domain/intel/openvino/passes/op/clamp.py
onnxifier/domain/intel/openvino/passes/op/concat.py
onnxifier/domain/intel/openvino/passes/op/constant.py
onnxifier/domain/intel/openvino/passes/op/convert.py
onnxifier/domain/intel/openvino/passes/op/convolution.py
onnxifier/domain/intel/openvino/passes/op/convolution_backprop_data.py
onnxifier/domain/intel/openvino/passes/op/depth_to_space.py
onnxifier/domain/intel/openvino/passes/op/divide.py
onnxifier/domain/intel/openvino/passes/op/fake_quantize.py
onnxifier/domain/intel/openvino/passes/op/floormod.py
onnxifier/domain/intel/openvino/passes/op/gather.py
onnxifier/domain/intel/openvino/passes/op/gather_elements.py
onnxifier/domain/intel/openvino/passes/op/gather_nd.py
onnxifier/domain/intel/openvino/passes/op/greater_equal.py
onnxifier/domain/intel/openvino/passes/op/group_normalization.py
onnxifier/domain/intel/openvino/passes/op/hard_sigmoid.py
onnxifier/domain/intel/openvino/passes/op/hsigmoid.py
onnxifier-2.0.0.dist-info/entry_points.txt
onnxifier-2.0.0.dist-info/licenses/LICENSE
onnxifier-2.0.0.dist-info/WHEEL
onnxifier-2.0.0.dist-info/METADATA
onnxifier-2.0.0.dist-info/RECORD
